paystackpy/__init__.py
paystackpy/apiConfig.py
paystackpy/customers.py
paystackpy/errors.py
paystackpy/misc.py
paystackpy/plans.py
paystackpy/transactions.py
paystackpy/transfers.py
paystackpy/utils.py
paystackpy/verification.py
paystackpy/version.py
paystackpy-0.0.6.dist-info/LICENSE
paystackpy-0.0.6.dist-info/METADATA
paystackpy-0.0.6.dist-info/WHEEL
paystackpy-0.0.6.dist-info/top_level.txt
paystackpy-0.0.6.dist-info/RECORD
