Metadata-Version: 2.1
Name: paystackpy
Version: 0.0.6
Summary: A Paystack API wrapper with python
Home-page: https://github.com/ConfidenceYobo/paystackpy
Author: Confidence Yobo
Author-email: confiyobo@gmail.com
License: UNKNOWN
Download-URL: https://github.com/ConfidenceYobo/paystackpy/archive/v0.0.6.tar.gz
Platform: UNKNOWN
Classifier: Programming Language :: Python :: 3
Classifier: License :: OSI Approved :: MIT License
Classifier: Operating System :: OS Independent
Requires-Dist: requests
Requires-Dist: simplejson
